Metadata-Version: 2.1
Name: backupcpy
Version: 1.0.0
Summary: Backupcpy is a tiny and elegant backup archive assembler
Home-page: https://github.com/Addvilz/backupcpy
Author: Addvilz
Author-email: mrtreinis@gmail.com
License: Apache 2.0
Download-URL: https://github.com/Addvilz/backupcpy
Platform: UNIX
Classifier: Development Status :: 5 - Production/Stable
Classifier: Environment :: Console
Classifier: Intended Audience :: Developers
Classifier: Intended Audience :: System Administrators
Classifier: License :: OSI Approved :: Apache Software License
Classifier: Operating System :: MacOS :: MacOS X
Classifier: Operating System :: POSIX :: Linux
Classifier: Operating System :: POSIX
Classifier: Operating System :: Unix
Classifier: Programming Language :: Python :: 3 :: Only
Classifier: Topic :: System :: Archiving :: Backup
